CHANGELOG
COPYRIGHT
README
TODO
ez_setup.py
setup.py
optparse_gui/__init__.py
optparse_gui.egg-info/PKG-INFO
optparse_gui.egg-info/SOURCES.txt
optparse_gui.egg-info/dependency_links.txt
optparse_gui.egg-info/top_level.txt
optparse_gui.egg-info/zip-safe
tests/__init__.py
tests/test.py