Metadata-Version: 1.0
Name: optparse_gui
Version: 0.1
Summary: import optparse_gui as optparse - wx gui frontend for optparse
Home-page: http://optparse-gui.googlecode.com
Author: slider fry
Author-email: slider.fry@gmail.com
License: BSD
Download-URL: http://optparse-gui.googlecode.com/files/optparse_gui-0.1.zip
Keywords: python gui wx commandline optparse
Platform: UNKNOWN
Classifier: Development Status :: 3 - Alpha
Classifier: Environment :: Win32 (MS Windows)
Classifier: Environment :: X11 Applications
Classifier: Intended Audience :: Developers
Classifier: License :: OSI Approved :: BSD License
Classifier: Operating System :: Microsoft :: Windows
Classifier: Operating System :: POSIX
Classifier: Operating System :: OS Independent
Classifier: Operating System :: MacOS
Classifier: Programming Language :: Python
Classifier: Topic :: Software Development
